sta2stac/__init__.py
sta2stac/_version.py
sta2stac/assets.py
sta2stac/creator.py
sta2stac/harvester.py
sta2stac/logger.py
sta2stac/main.py
sta2stac/py.typed
sta2stac/analysers/__init__.py
sta2stac/analysers/existence_validator.py
sta2stac/analysers/item_info_retriever.py
sta2stac/analysers/processing.py
sta2stac/analysers/properties_verifier.py
sta2stac/analysers/utils.py
sta2stac/extensions/__init__.py
sta2stac/extensions/datacube.py
sta2stac/extensions/extra_metadata.py
sta2stac/statics/__init__.py
sta2stac/statics/constants.py
sta2stac-2.0.1.dist-info/CC-BY-4.0.txt
sta2stac-2.0.1.dist-info/CC0-1.0.txt
sta2stac-2.0.1.dist-info/EUPL-1.2.txt
sta2stac-2.0.1.dist-info/METADATA
sta2stac-2.0.1.dist-info/WHEEL
sta2stac-2.0.1.dist-info/top_level.txt
sta2stac-2.0.1.dist-info/RECORD
