Metadata-Version: 2.1
Name: sta2stac
Version: 2.0.1
Summary: A Python Ecosystem for Harvesting Time Series data information from SensorthingsAPI (STA) and Cultivating STAC-Metadata.
Author-email: Mostafa Hadizadeh <mostafa.hadizadeh@kit.edu>
Maintainer-email: Mostafa Hadizadeh <mostafa.hadizadeh@kit.edu>
License: EUPL-1.2
Project-URL: Homepage, https://codebase.helmholtz.cloud/cat4kit/ds2stac/sta2stac
Project-URL: Documentation, https://sta2stac.readthedocs.io/en/latest/
Project-URL: Source, https://codebase.helmholtz.cloud/cat4kit/ds2stac/sta2stac
Project-URL: Tracker, https://codebase.helmholtz.cloud/cat4kit/ds2stac/sta2stac/issues/
Classifier: Intended Audience :: Developers
Classifier: License :: OSI Approved :: European Union Public Licence 1.2 (EUPL 1.2)
Classifier: Operating System :: OS Independent
Classifier: Programming Language :: Python
Classifier: Programming Language :: Python :: 3
Classifier: Programming Language :: Python :: 3 :: Only
Classifier: Programming Language :: Python :: 3.9
Classifier: Programming Language :: Python :: 3.10
Classifier: Typing :: Typed
Requires-Python: >=3.9
License-File: LICENSES/CC-BY-4.0.txt
License-File: LICENSES/CC0-1.0.txt
License-File: LICENSES/EUPL-1.2.txt
Requires-Dist: pystac
Requires-Dist: tqdm
Requires-Dist: pytz
Requires-Dist: urllib3 ==1.26.6
Requires-Dist: requests
Requires-Dist: shapely ==2.0.1
Provides-Extra: dev
Requires-Dist: sta2stac[testsite] ; extra == 'dev'
Requires-Dist: sta2stac[docs] ; extra == 'dev'
Requires-Dist: PyYAML ; extra == 'dev'
Requires-Dist: types-PyYAML ; extra == 'dev'
Requires-Dist: types-requests ; extra == 'dev'
Requires-Dist: types-pytz ; extra == 'dev'
Provides-Extra: docs
Requires-Dist: autodocsumm ; extra == 'docs'
Requires-Dist: sphinx-rtd-theme ; extra == 'docs'
Requires-Dist: hereon-netcdf-sphinxext ; extra == 'docs'
Requires-Dist: sphinx-design ; extra == 'docs'
Provides-Extra: testsite
Requires-Dist: tox ; extra == 'testsite'
Requires-Dist: isort ==5.12.0 ; extra == 'testsite'
Requires-Dist: black ==23.1.0 ; extra == 'testsite'
Requires-Dist: blackdoc ==0.3.8 ; extra == 'testsite'
Requires-Dist: flake8 ==6.0.0 ; extra == 'testsite'
Requires-Dist: pre-commit ; extra == 'testsite'
Requires-Dist: mypy ; extra == 'testsite'
Requires-Dist: pytest-cov ; extra == 'testsite'
Requires-Dist: reuse ; extra == 'testsite'
Requires-Dist: cffconvert ; extra == 'testsite'
Requires-Dist: types-requests ; extra == 'testsite'
Requires-Dist: types-pytz ; extra == 'testsite'
